resilient_result/__init__.py
resilient_result/circuit.py
resilient_result/defaults.py
resilient_result/errors.py
resilient_result/policies.py
resilient_result/rate_limit.py
resilient_result/resilient.py
resilient_result/result.py
resilient_result/timeout.py
resilient_result-0.4.1.dist-info/LICENSE
resilient_result-0.4.1.dist-info/METADATA
resilient_result-0.4.1.dist-info/WHEEL
resilient_result-0.4.1.dist-info/RECORD
