Metadata-Version: 2.3
Name: resilient-result
Version: 0.4.1
Summary: Resilient decorators that return Result types instead of throwing exceptions
License: MIT
Keywords: result,error-handling,resilient,retry,timeout,async
Author: resilient-result contributors
Requires-Python: >=3.8,<4.0
Classifier: Development Status :: 4 - Beta
Classifier: Intended Audience :: Developers
Classifier: License :: OSI Approved :: MIT License
Classifier: Programming Language :: Python :: 3
Classifier: Programming Language :: Python :: 3.8
Classifier: Programming Language :: Python :: 3.9
Classifier: Programming Language :: Python :: 3.10
Classifier: Programming Language :: Python :: 3.11
Classifier: Programming Language :: Python :: 3.12
Classifier: Programming Language :: Python :: 3.13
Classifier: Topic :: Internet :: WWW/HTTP
Classifier: Topic :: Software Development :: Libraries :: Python Modules
Classifier: Topic :: System :: Networking
Project-URL: Homepage, https://github.com/iteebz/resilient-result
Project-URL: Repository, https://github.com/iteebz/resilient-result
